.editorconfig
.gitignore
.nojekyll
.travis.yml
AUTHORS.rst
CONTRIBUTING.rst
HISTORY.rst
LICENSE
MANIFEST.in
Makefile
README.rst
build_tools_and_enviorment_checker.py
index.html
notes.txt
requirements.txt
setup.cfg
setup.py
tox.ini
docs/Makefile
docs/authors.rst
docs/conf.py
docs/contributing.rst
docs/history.rst
docs/index.rst
docs/installation.rst
docs/make.bat
docs/modules.rst
docs/myhdlpeek.myhdl.rst
docs/myhdlpeek.nmigen.rst
docs/myhdlpeek.rst
docs/readme.rst
docs/usage.rst
docs/xess.ico
docs/xess.png
docs/_build/doctrees/authors.doctree
docs/_build/doctrees/contributing.doctree
docs/_build/doctrees/environment.pickle
docs/_build/doctrees/history.doctree
docs/_build/doctrees/index.doctree
docs/_build/doctrees/installation.doctree
docs/_build/doctrees/modules.doctree
docs/_build/doctrees/myhdlpeek.doctree
docs/_build/doctrees/readme.doctree
docs/_build/doctrees/usage.doctree
docs/_build/singlehtml/.buildinfo
docs/_build/singlehtml/index.html
docs/_build/singlehtml/objects.inv
docs/_build/singlehtml/_static/basic.css
docs/_build/singlehtml/_static/classic.css
docs/_build/singlehtml/_static/default.css
docs/_build/singlehtml/_static/doctools.js
docs/_build/singlehtml/_static/file.png
docs/_build/singlehtml/_static/jquery.js
docs/_build/singlehtml/_static/minus.png
docs/_build/singlehtml/_static/plus.png
docs/_build/singlehtml/_static/pygments.css
docs/_build/singlehtml/_static/searchtools.js
docs/_build/singlehtml/_static/sidebar.js
docs/_build/singlehtml/_static/underscore.js
examples/complete.ipynb
examples/custom.css
examples/edit_html.txt
myhdlpeek/__init__.py
myhdlpeek/pckg_info.py
myhdlpeek/peekerbase.py
myhdlpeek/trace.py
myhdlpeek.egg-info/PKG-INFO
myhdlpeek.egg-info/SOURCES.txt
myhdlpeek.egg-info/dependency_links.txt
myhdlpeek.egg-info/entry_points.txt
myhdlpeek.egg-info/not-zip-safe
myhdlpeek.egg-info/requires.txt
myhdlpeek.egg-info/top_level.txt
myhdlpeek/amaranth/__init__.py
myhdlpeek/amaranth/peeker.py
myhdlpeek/myhdl/__init__.py
myhdlpeek/myhdl/peeker.py
tests/state_test.py
tests/test1.py
tests/test1.py~
tests/test2.py
tests/test_dataframe.py
tests/test_myhdlpeek.py
tests/trigger_test1.py