Metadata-Version: 2.1
Name: myhdlpeek
Version: 1.0.0
Summary: Peek at signals in a MyHDL or Amaranth digital system simulation.
Home-page: https://github.com/devbisme/myhdlpeek
Author: Dave Vandenbout
Author-email: dave@vdb.name
License: MIT
Keywords: myhdlpeek
Classifier: Development Status :: 5 - Production/Stable
Classifier: Intended Audience :: Developers
Classifier: License :: OSI Approved :: MIT License
Classifier: Natural Language :: English
Classifier: Programming Language :: Python :: 3 :: Only
Classifier: Topic :: Scientific/Engineering :: Electronic Design Automation (EDA)
License-File: LICENSE
License-File: AUTHORS.rst
